guilogger/__init__.py
guilogger-0.5.dist-info/METADATA
guilogger-0.5.dist-info/WHEEL
guilogger-0.5.dist-info/top_level.txt
guilogger-0.5.dist-info/RECORD
