Metadata-Version: 2.1
Name: guilogger
Version: 0.5
Summary: GUI logger + progress bar
Home-page: https://github.com/ericgj/guilogger
Author: Eric Gjertsen
License: MIT
Classifier: Programming Language :: Python :: 3
Classifier: Operating System :: OS Independent
Classifier: Development Status :: 2 - Pre-Alpha
Classifier: License :: OSI Approved :: MIT License
Provides-Extra: test
